{
  "volume_id": "BB1",
  "page_number": 494,
  "raw_text": "21st\nKordun\nCorps\n,\nHQ\nVojnic\n11th Infantry Brigade, HQ Vojnic\n13th Infantry Brigade, HQ Slunj\n19th Infantry Brigade, HQ Vrginmost\n21st Light Air Defense Artillery -Rocket Battalion, HQ Slunj\n21st Military Police Company, HQ Vojnic\n39th Banija\nCorps\n,\nHQ\nPetrinja\n24th Infantry Brigade, HQ Glina\n26th Infantry Brigade, HQ Kostajnica\n31st Infantry Brigade, HQ Petrinja\n33rd Infantry Brigade, HQ Dvor\n39th Light Air Defense Artillery -Rocket Battalion, HQ Petrinja\n39th\nRear Base\n,\nHQ\nKostajnica\n457",
  "clean_text": "21st\nKordun\nCorps\n,\nHQ\nVojnic\n11th Infantry Brigade, HQ Vojnic\n13th Infantry Brigade, HQ Slunj\n19th Infantry Brigade, HQ Vrginmost\n21st Light Air Defense Artillery -Rocket Battalion, HQ Slunj\n21st Military Police Company, HQ Vojnic\n39th Banija\nCorps\n,\nHQ\nPetrinja\n24th Infantry Brigade, HQ Glina\n26th Infantry Brigade, HQ Kostajnica\n31st Infantry Brigade, HQ Petrinja\n33rd Infantry Brigade, HQ Dvor\n39th Light Air Defense Artillery -Rocket Battalion, HQ Petrinja\n39th\nRear Base\n,\nHQ\nKostajnica\n457",
  "ocr_applied": false,
  "text_hash": "c5a2d51a6036bf11e315acc31be6f5bb55bedbb65a2fcaf8a076cc0cf2f7fbba",
  "clean_text_hash": "c5a2d51a6036bf11e315acc31be6f5bb55bedbb65a2fcaf8a076cc0cf2f7fbba",
  "layout_blocks": [],
  "tables": [],
  "figures": [],
  "map_regions": [],
  "notes": []
}
