{
  "volume_id": "BB2",
  "page_number": 528,
  "raw_text": "have been made did not even survive contact between\nthe allies .\nthan ownership of traditionally-Croat Kupres, and that\nvying for the town could well reignite the Croat-Mus\nlim war that had already proven so destructive to both\nsides.\nThe\noperation\nto\ncapture\nKupres\nwas\nthe\nfirst\nvisible\nexample\nof\nmajor\nCroat\n-\nMuslim\ncooperation\nin\nmili\ntary\noperations\nsince\nthe\nsigning\nof\nthe\nFederation\nagreement\nin\nMarch\n1994.\nAs\nsuch\n,\nit\nwas\nboth\na\ntest\ncase\nand\na  public\nrelations\nexample\nof\nmilitary\ncoop\neration\n.\nIf\nit\nis\ntrue\nthat\nno\nmilitary\nplan  survives\ncon\ntact\nwith\nthe\nenemy\n,\nin\nthis\ncase\nwhatever\nplans\nmay\nFor all its flaws in planning and execution, the Croat\nMuslim capture of Kupres was a step in the right\ndirection-militarily, politically, and geographi\ncally—and a step closer to both factions' ultimate\nobjective of Jajce. But it left unclear whether the\nARBiH and the HVO were advancing down the road\nalongside each other or racing each other to the finish .\n509",
  "clean_text": "have been made did not even survive contact between\nthe allies .\nthan ownership of traditionally-Croat Kupres, and that\nvying for the town could well reignite the Croat-Mus\nlim war that had already proven so destructive to both\nsides.\nThe\noperation\nto\ncapture\nKupres\nwas\nthe\nfirst\nvisible\nexample\nof\nmajor\nCroat\n-\nMuslim\ncooperation\nin\nmili\ntary\noperations\nsince\nthe\nsigning\nof\nthe\nFederation\nagreement\nin\nMarch\n1994.\nAs\nsuch\n,\nit\nwas\nboth\na\ntest\ncase\nand\na  public\nrelations\nexample\nof\nmilitary\ncoop\neration\n.\nIf\nit\nis\ntrue\nthat\nno\nmilitary\nplan  survives\ncon\ntact\nwith\nthe\nenemy\n,\nin\nthis\ncase\nwhatever\nplans\nmay\nFor all its flaws in planning and execution, the Croat\nMuslim capture of Kupres was a step in the right\ndirection-militarily, politically, and geographi\ncally—and a step closer to both factions' ultimate\nobjective of Jajce. But it left unclear whether the\nARBiH and the HVO were advancing down the road\nalongside each other or racing each other to the finish .\n509",
  "ocr_applied": false,
  "text_hash": "cca19ee68d967d655105277eb2b71d26ce7a04485596aab6bdb6debe089a3077",
  "clean_text_hash": "cca19ee68d967d655105277eb2b71d26ce7a04485596aab6bdb6debe089a3077",
  "layout_blocks": [],
  "tables": [],
  "figures": [],
  "map_regions": [],
  "notes": []
}
